mongodb_connect/__init__.py
mongodb_connect/mongo_crud.py
mlops_package_mmtg-0.0.3.dist-info/METADATA
mlops_package_mmtg-0.0.3.dist-info/WHEEL
mlops_package_mmtg-0.0.3.dist-info/top_level.txt
mlops_package_mmtg-0.0.3.dist-info/RECORD
