Metadata-Version: 2.1
Name: mlops-package-mmtg
Version: 0.0.3
Summary: A python package for connecting with database.
Home-page: https://github.com/mm0177/mlops-mmtg123
Author: mm0177
Author-email: mm0177@srmist.edu.in
License: MIT
Project-URL: Bug Tracker, https://github.com/mm0177/mlops-mmtg123/issues
Classifier: Programming Language :: Python :: 3.7
Classifier: Programming Language :: Python :: 3.8
Classifier: Programming Language :: Python :: 3.9
Classifier: Operating System :: OS Independent
Requires-Python: >=3.7
Requires-Dist: ensure==1.0.2
Requires-Dist: py-youtube==1.1.7
Provides-Extra: testing
Requires-Dist: pytest>=7.1.3; extra == "testing"
Requires-Dist: mypy>=0.971; extra == "testing"
Requires-Dist: flake8>=5.0.4; extra == "testing"
Requires-Dist: tox>=3.25.1; extra == "testing"
Requires-Dist: black>=22.8.0; extra == "testing"
